watson/__init__.py
watson/events/__init__.py
watson/events/collections.py
watson/events/dispatcher.py
watson/events/types.py
watson_events-1.0.4.dist-info/AUTHORS
watson_events-1.0.4.dist-info/LICENSE
watson_events-1.0.4.dist-info/METADATA
watson_events-1.0.4.dist-info/WHEEL
watson_events-1.0.4.dist-info/top_level.txt
watson_events-1.0.4.dist-info/RECORD
