Metadata-Version: 2.1
Name: watson-events
Version: 1.0.4
Summary: Trigger and handle event flow with your application.
Home-page: http://github.com/watsonpy/watson-events
Author: Simon Coulton
Author-email: simon@bespohk.com
License: Copyright (c) Bespohk and individual contributors.
Requires-Dist: watson-common (>=1.1.0)
Provides-Extra: test
Requires-Dist: pytest ; extra == 'test'
Requires-Dist: pytest-cov ; extra == 'test'
Requires-Dist: coverage ; extra == 'test'
Requires-Dist: coveralls ; extra == 'test'
